[
    {
        "id": 1717920100000,
        "reporter": "張小明",
        "date": "2025-06-09",
        "projectCode": "PRJ-2025-001",
        "workHours": 8,
        "content": "完成首頁設計稿的初版，包含 Header、Hero Section 和主要功能區塊。與設計師確認色彩配置和字體選擇。開始進行響應式設計的規劃。",
        "blocker": "等待客戶提供 Logo 的向量檔案，目前使用暫時版本。",
        "needHelp": "否",
        "plan": "明日將完成首頁的響應式設計，並開始製作產品頁面的設計稿。",
        "createdAt": "2025-06-09T18:30:00.000Z"
    },
    {
        "id": 1717920200000,
        "reporter": "李小華",
        "date": "2025-06-09",
        "projectCode": "PRJ-2025-002",
        "workHours": 7.5,
        "content": "完成客戶資料模型設計，建立基本的 CRUD API。實作客戶新增、修改、刪除功能。進行初步的資料驗證機制。",
        "blocker": "需要與業務部門確認客戶資料的必填欄位和格式要求。",
        "needHelp": "是",
        "plan": "明日與業務部門開會討論需求細節，並繼續完善 API 功能。",
        "createdAt": "2025-06-09T19:15:00.000Z"
    },
    {
        "id": 1717920300000,
        "reporter": "陳小芳",
        "date": "2025-06-09",
        "projectCode": "PRJ-2025-004",
        "workHours": 6,
        "content": "完成課程管理後台的基本功能，包含課程新增、編輯、分類管理。測試課程內容上傳功能，支援影片和文件格式。",
        "blocker": "",
        "needHelp": "否",
        "plan": "明日開始開發學員進度追蹤功能，並設計考試系統的資料結構。",
        "createdAt": "2025-06-09T17:45:00.000Z"
    },
    {
        "id": 1717834800000,
        "reporter": "張小明",
        "date": "2025-06-08",
        "projectCode": "PRJ-2025-001",
        "workHours": 8,
        "content": "完成網站架構規劃和技術選型。確定使用 Next.js 14、Tailwind CSS 和 Framer Motion。建立專案基礎架構和開發環境。",
        "blocker": "",
        "needHelp": "否",
        "plan": "明日開始進行首頁設計稿製作，並與 UI/UX 團隊討論設計方向。",
        "createdAt": "2025-06-08T18:00:00.000Z"
    },
    {
        "id": 1717834900000,
        "reporter": "李小華",
        "date": "2025-06-08",
        "projectCode": "PRJ-2025-002",
        "workHours": 7,
        "content": "完成專案環境建置，包含 Node.js 後端和 Vue.js 前端。建立基本的專案結構和資料庫連線設定。",
        "blocker": "資料庫伺服器配置還在等待 IT 部門處理。",
        "needHelp": "是",
        "plan": "明日開始設計資料庫 Schema，並建立客戶管理的基本 API。",
        "createdAt": "2025-06-08T18:30:00.000Z"
    },
    {
        "id": 1717835000000,
        "reporter": "陳小芳",
        "date": "2025-06-08",
        "projectCode": "PRJ-2025-004",
        "workHours": 6.5,
        "content": "與 HR 部門進行需求確認會議，整理課程分類和權限管理需求。開始設計系統架構和資料流程。",
        "blocker": "",
        "needHelp": "否",
        "plan": "明日開始建立開發環境，並開始課程管理模組的開發。",
        "createdAt": "2025-06-08T17:30:00.000Z"
    },
    {
        "id": 1717748400000,
        "reporter": "張小明",
        "date": "2025-06-07",
        "projectCode": "PRJ-2025-001",
        "workHours": 8,
        "content": "與客戶進行專案啟動會議，確認專案範圍、時程和交付項目。收集現有網站的問題點和改善需求。建立專案文件和時程規劃。",
        "blocker": "",
        "needHelp": "否",
        "plan": "明日開始進行技術架構規劃和開發環境建置。",
        "createdAt": "2025-06-07T19:00:00.000Z"
    },
    {
        "id": 1717748500000,
        "reporter": "李小華",
        "date": "2025-06-07",
        "projectCode": "PRJ-2025-002",
        "workHours": 4,
        "content": "參加專案啟動會議，了解 CRM 系統的功能需求和使用者情境。開始研究相關技術文件和最佳實踐。",
        "blocker": "",
        "needHelp": "否",
        "plan": "明日開始建立開發環境和專案架構規劃。",
        "createdAt": "2025-06-07T16:00:00.000Z"
    },
    {
        "id": 1717662000000,
        "reporter": "陳小芳",
        "date": "2025-06-06",
        "projectCode": "PRJ-2025-004",
        "workHours": 8,
        "content": "完成使用者需求調研，訪談了 15 位不同部門的員工。整理培訓需求和系統功能期望。製作需求分析報告。",
        "blocker": "部分主管的時間安排困難，還有 3 位主管需要訪談。",
        "needHelp": "否",
        "plan": "明日完成剩餘的使用者訪談，並開始系統功能規劃。",
        "createdAt": "2025-06-06T18:45:00.000Z"
    },
    {
        "id": 1717575600000,
        "reporter": "劉志明",
        "date": "2025-06-05",
        "projectCode": "PRJ-2025-005",
        "workHours": 8,
        "content": "完成資料庫效能優化專案的最終測試。效能提升達到 35%，超過原定目標。完成專案文件整理和移交準備。",
        "blocker": "",
        "needHelp": "否",
        "plan": "明日進行專案結案報告，並安排系統維護交接。",
        "createdAt": "2025-06-05T17:30:00.000Z"
    }
]